dutVulnScanner/__init__.py
dutVulnScanner/__main__.py
dutVulnScanner/assets/logo.ico
dutVulnScanner/assets/logo.png
dutVulnScanner/cli/__init__.py
dutVulnScanner/cli/commands/__init__.py
dutVulnScanner/cli/commands/doctor.py
dutVulnScanner/cli/commands/profile.py
dutVulnScanner/cli/commands/report.py
dutVulnScanner/cli/commands/scan.py
dutVulnScanner/cli/commands/settings.py
dutVulnScanner/cli/main.py
dutVulnScanner/cli/shell.py
dutVulnScanner/core/__init__.py
dutVulnScanner/core/checkpoint.py
dutVulnScanner/core/config.py
dutVulnScanner/core/correlation.py
dutVulnScanner/core/dependency_manager.py
dutVulnScanner/core/orchestrator.py
dutVulnScanner/core/schema.py
dutVulnScanner/core/tool_registry.py
dutVulnScanner/notification/__init__.py
dutVulnScanner/notification/base.py
dutVulnScanner/notification/discord.py
dutVulnScanner/notification/manager.py
dutVulnScanner/notification/README.md
dutVulnScanner/notification/toast.py
dutVulnScanner/plugins/__init__.py
dutVulnScanner/plugins/base.py
dutVulnScanner/plugins/recon/__init__.py
dutVulnScanner/plugins/recon/httpx.py
dutVulnScanner/plugins/recon/naabu.py
dutVulnScanner/plugins/recon/nmap.py
dutVulnScanner/plugins/recon/subfinder.py
dutVulnScanner/plugins/recon/whatweb.py
dutVulnScanner/plugins/recon/whois.py
dutVulnScanner/plugins/scanners/__init__.py
dutVulnScanner/plugins/scanners/nikto.py
dutVulnScanner/plugins/scanners/nuclei.py
dutVulnScanner/plugins/scanners/sslscan.py
dutVulnScanner/plugins/scanners/testssl.py
dutVulnScanner/plugins/validators/__init__.py
dutVulnScanner/plugins/validators/dalfox.py
dutVulnScanner/plugins/validators/hydra.py
dutVulnScanner/plugins/validators/sqlmap.py
dutVulnScanner/profiles/backend.yaml
dutVulnScanner/profiles/deep_test.yaml
dutVulnScanner/profiles/discovery_full.yaml
dutVulnScanner/profiles/full_scan.yaml
dutVulnScanner/profiles/infra.yaml
dutVulnScanner/profiles/quick.yaml
dutVulnScanner/profiles/README.md
dutVulnScanner/profiles/recon.yaml
dutvulnscanner-0.4.0.dist-info/entry_points.txt
dutvulnscanner-0.4.0.dist-info/licenses/LICENSE
dutvulnscanner-0.4.0.dist-info/METADATA
dutvulnscanner-0.4.0.dist-info/WHEEL
dutvulnscanner-0.4.0.dist-info/RECORD
