Metadata-Version: 2.4
Name: dutVulnScanner
Version: 0.4.0
Summary: DUT Vulnerability Scanner - A comprehensive security scanning tool with plugin-based architecture
License: DUT
License-File: LICENSE
Keywords: security,vulnerability,scanner,pentesting,network,cli,tool
Author: Phan Văn Tài
Author-email: taiphanvan2403@gmail.com
Maintainer: Phan Văn Tài
Maintainer-email: taiphanvan2403@gmail.com
Requires-Python: >=3.10,<4.0
Classifier: License :: Other/Proprietary License
Classifier: Programming Language :: Python :: 3
Classifier: Programming Language :: Python :: 3.10
Classifier: Programming Language :: Python :: 3.11
Classifier: Programming Language :: Python :: 3.12
Classifier: Programming Language :: Python :: 3.13
Classifier: Programming Language :: Python :: 3.14
Requires-Dist: firebase-admin (>=7.1.0,<8.0.0)
Requires-Dist: google-generativeai (>=0.3.0,<1.0.0)
Requires-Dist: plyer (>=2.1.0,<3.0.0)
Requires-Dist: psutil (>=7.1.3,<8.0.0)
Requires-Dist: pydantic (>=2.12.3,<3.0.0)
Requires-Dist: python-dotenv (>=1.2.1,<2.0.0)
Requires-Dist: pyyaml (>=6.0.3,<7.0.0)
Requires-Dist: reportlab (>=4.0.0,<5.0.0)
Requires-Dist: requests (>=2.31.0,<3.0.0)
Requires-Dist: rich (>=14.2.0,<15.0.0)
Requires-Dist: typer[all] (>=0.20.0,<0.21.0)
Project-URL: Changelog, https://github.com/DinhManhAVG/CLI-Cross-Platform/blob/main/CHANGELOG.md
Project-URL: Documentation, https://github.com/DinhManhAVG/CLI-Cross-Platform#readme
Project-URL: Homepage, https://github.com/DinhManhAVG/CLI-Cross-Platform
Project-URL: Issues, https://github.com/DinhManhAVG/CLI-Cross-Platform/issues
Project-URL: Repository, https://github.com/DinhManhAVG/CLI-Cross-Platform
